pipelinemaker
